LICENSE
MANIFEST.in
setup.cfg
setup.py
pyhoe/__init__.py
pyhoe/delegator.py
pyhoe.egg-info/PKG-INFO
pyhoe.egg-info/SOURCES.txt
pyhoe.egg-info/dependency_links.txt
pyhoe.egg-info/entry_points.txt
pyhoe.egg-info/top_level.txt
pyhoe/main/__init__.py
pyhoe/main/command.py
pyhoe/sow/__init__.py
pyhoe/sow/command.py
pyhoe/sow/delegator.py
pyhoe/sow/executor.py
pyhoe/sow/templates/package/.DS_Store
pyhoe/sow/templates/package/.gitignore
pyhoe/sow/templates/package/CHANGELOG.md
pyhoe/sow/templates/package/MANIFEST.in
pyhoe/sow/templates/package/MIT-LICENSE
pyhoe/sow/templates/package/README.md
pyhoe/sow/templates/package/setup.cfg
pyhoe/sow/templates/package/setup.py
pyhoe/sow/templates/package/tox.ini
pyhoe/sow/templates/package/PROJECT_NAME/.DS_Store
pyhoe/sow/templates/package/PROJECT_NAME/__init__.py
pyhoe/sow/templates/package/PROJECT_NAME/main.py
pyhoe/sow/templates/package/tests/PROJECT_NAME_tests.py
pyhoe/sow/templates/package/tests/__init__.py
pyhoe/utils/__init__.py
pyhoe/utils/console.py
pyhoe/utils/git.py
pyhoe/utils/network.py
pyhoe/utils/virtualenv.py
tests/__init__.py
tests/test_utils/__init__.py
tests/test_utils/test_git.py
tests/test_utils/test_network.py
tests/test_utils/test_virtualenv.py