Metadata-Version: 1.0
Name: pyhoe
Version: 0.0.1a5
Summary: A project skeleton generator.
Home-page: https://github.com/modocache/pyhoe
Author: modocache
Author-email: modocache@gmail.com
License: UNKNOWN
Keywords: project setup skeleton
Platform: UNKNOWN
Classifier: Programming Language :: Python :: 2
Classifier: Programming Language :: Python :: 3
Classifier: Development Status :: 2 - Pre-Alpha
Classifier: Operating System :: MacOS
Classifier: Operating System :: Unix
Classifier: Intended Audience :: Developers
Classifier: Topic :: Software Development :: Build Tools
Classifier: Topic :: Software Development :: Code Generators
Classifier: Topic :: Software Development :: Debuggers
